js_lib_ag_grid_community/__init__.py
js_lib_ag_grid_community/apps.py
js_lib_ag_grid_community/static/ag-grid-community/ag-grid-community.js
js_lib_ag_grid_community/static/ag-grid-community/ag-grid-community.min.js
js_lib_ag_grid_community/static/ag-grid-community/ag-grid-community.min.noStyle.js
js_lib_ag_grid_community/static/ag-grid-community/ag-grid-community.noStyle.js
js_lib_ag_grid_community/static/ag-grid-community/styles/ag-grid.css
js_lib_ag_grid_community/static/ag-grid-community/styles/ag-grid.min.css
js_lib_ag_grid_community/static/ag-grid-community/styles/ag-grid.scss
js_lib_ag_grid_community/static/ag-grid-community/styles/ag-theme-alpine-dark.css
js_lib_ag_grid_community/static/ag-grid-community/styles/ag-theme-alpine-dark.min.css
js_lib_ag_grid_community/static/ag-grid-community/styles/ag-theme-alpine.css
js_lib_ag_grid_community/static/ag-grid-community/styles/ag-theme-alpine.min.css
js_lib_ag_grid_community/static/ag-grid-community/styles/ag-theme-balham-dark.css
js_lib_ag_grid_community/static/ag-grid-community/styles/ag-theme-balham-dark.min.css
js_lib_ag_grid_community/static/ag-grid-community/styles/ag-theme-balham.css
js_lib_ag_grid_community/static/ag-grid-community/styles/ag-theme-balham.min.css
js_lib_ag_grid_community/static/ag-grid-community/styles/ag-theme-blue.css
js_lib_ag_grid_community/static/ag-grid-community/styles/ag-theme-blue.min.css
js_lib_ag_grid_community/static/ag-grid-community/styles/ag-theme-bootstrap.css
js_lib_ag_grid_community/static/ag-grid-community/styles/ag-theme-bootstrap.min.css
js_lib_ag_grid_community/static/ag-grid-community/styles/ag-theme-dark.css
js_lib_ag_grid_community/static/ag-grid-community/styles/ag-theme-dark.min.css
js_lib_ag_grid_community/static/ag-grid-community/styles/ag-theme-fresh.css
js_lib_ag_grid_community/static/ag-grid-community/styles/ag-theme-fresh.min.css
js_lib_ag_grid_community/static/ag-grid-community/styles/ag-theme-material.css
django_js_lib_ag_grid_community-25.3.0.0.dist-info/LICENSE.txt
django_js_lib_ag_grid_community-25.3.0.0.dist-info/METADATA
django_js_lib_ag_grid_community-25.3.0.0.dist-info/WHEEL
django_js_lib_ag_grid_community-25.3.0.0.dist-info/top_level.txt
django_js_lib_ag_grid_community-25.3.0.0.dist-info/RECORD
