Metadata-Version: 2.1
Name: django-js-lib-ag-grid-community
Version: 25.3.0.0
Summary: AG Grid Community (repackaged for django)
Home-page: https://github.com/nonZero/django-js-lib-ag-grid-community
Author: Udi Oron
Author-email: udioron@gmail.com
License: BSD-2-Clause
Platform: UNKNOWN
Classifier: Environment :: Web Environment
Classifier: Framework :: Django
Classifier: Intended Audience :: Developers
Classifier: License :: OSI Approved :: BSD License
Classifier: Operating System :: OS Independent
Classifier: Programming Language :: Python
Classifier: Programming Language :: Python :: 3
Classifier: Programming Language :: Python :: 3 :: Only
Classifier: Programming Language :: Python :: 3.6
Classifier: Programming Language :: Python :: 3.7
Classifier: Programming Language :: Python :: 3.8
Classifier: Topic :: Internet :: WWW/HTTP
Classifier: Topic :: Internet :: WWW/HTTP :: Dynamic Content
License-File: LICENSE.txt
